mayan_api_client/__init__.py
mayan_api_client/classes.py
mayan_api_client/exceptions.py
mayan_api_client-0.5.0.dist-info/RECORD
mayan_api_client-0.5.0.dist-info/metadata.json
mayan_api_client-0.5.0.dist-info/METADATA
mayan_api_client-0.5.0.dist-info/DESCRIPTION.rst
mayan_api_client-0.5.0.dist-info/WHEEL
mayan_api_client-0.5.0.dist-info/top_level.txt
