Metadata-Version: 2.0
Name: mayan-api-client
Version: 0.5.0
Summary: Python client for the Mayan EDMS REST API.
Home-page: https://github.com/rosarior/mayan_api_client
Author: Roberto Rosario
Author-email: roberto.rosario@mayan-edms.com
License: ISCL
Keywords: mayan_api_client
Platform: UNKNOWN
Classifier: Development Status :: 2 - Pre-Alpha
Classifier: Intended Audience :: Developers
Classifier: License :: OSI Approved :: ISC License (ISCL)
Classifier: Natural Language :: English
Classifier: Programming Language :: Python :: 2
Classifier: Programming Language :: Python :: 2.6
Classifier: Programming Language :: Python :: 2.7
Classifier: Programming Language :: Python :: 3
Classifier: Programming Language :: Python :: 3.3
Classifier: Programming Language :: Python :: 3.4
Classifier: Programming Language :: Python :: 3.5
Requires-Dist: slumber (==0.7.1)
